storage_bucket/__init__.py
storage_bucket/bucket.py
storage_bucket/client.py
storage_bucket/create.py
storage_bucket/delete.py
storage_bucket/delete_file.py
storage_bucket/download_file.py
storage_bucket/list.py
storage_bucket/list_files.py
storage_bucket/upload_file.py
storage_bucket-3.0.0.dist-info/LICENSE
storage_bucket-3.0.0.dist-info/WHEEL
storage_bucket-3.0.0.dist-info/METADATA
storage_bucket-3.0.0.dist-info/RECORD
