Metadata-Version: 2.1
Name: storage-bucket
Version: 3.0.0
Summary: Easy to work with Google Cloud Platform Storage Bucket wrapper
Home-page: https://github.com/thomasborgen/storage-bucket
License: MIT
Keywords: Storage Bucket,GCP,Google Cloud Platform,monad,functional programming
Author: Thomas Borgen
Author-email: thomas@borgenit.no
Requires-Python: >=3.6,<4.0
Classifier: Development Status :: 4 - Beta
Classifier: Intended Audience :: Developers
Classifier: License :: OSI Approved :: MIT License
Classifier: Operating System :: OS Independent
Classifier: Programming Language :: Python :: 3
Classifier: Programming Language :: Python :: 3.10
Classifier: Programming Language :: Python :: 3.6
Classifier: Programming Language :: Python :: 3.7
Classifier: Programming Language :: Python :: 3.8
Classifier: Programming Language :: Python :: 3.9
Classifier: Topic :: Software Development :: Libraries :: Python Modules
Classifier: Topic :: Utilities
Requires-Dist: google-cloud-storage (>=1.42.3,<2.0.0)
Project-URL: Documentation, https://thomasborgen.github.io/storage-bucket
Project-URL: Repository, https://github.com/thomasborgen/storage-bucket
